diameter/__init__.py
diameter/message/__init__.py
diameter/message/_base.py
diameter/message/constants.py
diameter/message/packer.py
diameter/message/avp/__init__.py
diameter/message/avp/avp.py
diameter/message/avp/dictionary.py
diameter/message/avp/errors.py
diameter/message/avp/generator.py
diameter/message/avp/grouped.py
diameter/message/commands/__init__.py
diameter/message/commands/_attributes.py
diameter/message/commands/aa.py
diameter/message/commands/aa_mobile_node.py
diameter/message/commands/abort_session.py
diameter/message/commands/accounting.py
diameter/message/commands/capabilities_exchange.py
diameter/message/commands/credit_control.py
diameter/message/commands/device_watchdog.py
diameter/message/commands/diameter_eap.py
diameter/message/commands/disconnect_peer.py
diameter/message/commands/home_agent_mip.py
diameter/message/commands/location_info.py
diameter/message/commands/multimedia_auth.py
diameter/message/commands/push_profile.py
diameter/message/commands/re_auth.py
diameter/message/commands/registration_termination.py
diameter/message/commands/server_assignment.py
diameter/message/commands/session_termination.py
diameter/message/commands/spending_limit.py
diameter/message/commands/spending_status_notification.py
diameter/message/commands/user_authorization.py
diameter/node/__init__.py
diameter/node/_helpers.py
diameter/node/application.py
diameter/node/node.py
diameter/node/peer.py
python_diameter-0.8.4.dist-info/licenses/LICENSE
python_diameter-0.8.4.dist-info/METADATA
python_diameter-0.8.4.dist-info/WHEEL
python_diameter-0.8.4.dist-info/top_level.txt
python_diameter-0.8.4.dist-info/RECORD
