Metadata-Version: 2.4
Name: python-diameter
Version: 0.8.4
Summary: A diameter stack implemented in python
Author: Mikko Mensonen
License: MIT License
Project-URL: Documentation, https://mensonen.github.io/diameter/
Project-URL: Repository, https://github.com/mensonen/diameter
Classifier: License :: OSI Approved :: MIT License
Classifier: Development Status :: 4 - Beta
Classifier: Programming Language :: Python :: 3.11
Classifier: Topic :: Communications :: Telephony
Requires-Python: >=3.11
License-File: LICENSE
Dynamic: license-file
